vvc/5b0g0024_q1.v
// 模組名稱：mult6
// 功能：執行 6 位元無號整數乘法（a × b），結果為 12 位元 axb
module mult6 (
  input  [5:0] a,       // 乘數 a（6 位元）
  input  [5:0] b,       // 被乘數 b（6 位元）
  output [11:0] axb     // 輸出結果 axb（12 位元）
);
  reg [11:0] product;   // 暫存乘積結果
  integer i;            // 迴圈變數

  // 組合邏輯實作「shift and add」乘法器
  always @(*) begin
    product = 0;        // 初始值清零
    for (i = 0; i < 6; i = i + 1) begin
      if (b[i]) begin
        // 如果 b 的第 i 位為 1，則將 a 左移 i 位後加到 product
        product = product + (a << i);
      end
    end
  end

  assign axb = product; // 將乘積指定給輸出
endmodule


// 測試模組：模擬所有 a, b 組合並顯示結果
module test;
  reg [5:0] a, b;         // 測試輸入 a 和 b
  wire [11:0] axb;        // 輸出 axb

  // 實例化乘法器模組
  mult6 U1(a, b, axb);

  // 設定波形輸出檔案（供 gtkwave 使用）
  initial begin
    $dumpfile("vcd/5b0g0024_q1.vcd"); // 指定輸出波形檔名
    $dumpvars();                      // dump 所有變數
  end

  integer i;
  initial begin
    // 測試 6 位元 x 6 位元 所有可能組合（共 4096 次）
    for(i = 0; i < 4096; i = i + 1) begin
      #0 a = i[5:0];      // 取低 6 位給 a
         b = i[11:6];     // 取高 6 位給 b
      #10;                // 模擬間隔 10 ns
    end
    a = 0; b = 0;         // 模擬結束時重設輸入
  end

  // 每次輸入或輸出變動時印出模擬時間與結果
  always @(a or b or axb)
    $display("%d ns, a = %d, b = %d, axb = %d", $time, a, b, axb);

endmodule

vcd/5b0g0024_q1.vcd
$date
	Tue Apr 22 15:25:01 2025
$end
$version
	Icarus Verilog
$end
$timescale
	1s
$end
$scope module test $end
$var wire 12 ! axb [11:0] $end
$var reg 6 " a [5:0] $end
$var reg 6 # b [5:0] $end
$var integer 32 $ i [31:0] $end
$scope module U1 $end
$var wire 6 % a [5:0] $end
$var wire 12 & axb [11:0] $end
$var wire 6 ' b [5:0] $end
$var reg 12 ( product [11:0] $end
$var integer 32 ) i [31:0] $end
$upscope $end
$upscope $end
$enddefinitions $end
$comment Show the parameter values. $end
$dumpall
$end
#0
$dumpvars
b110 )
b0 (
b0 '
b0 &
b0 %
b0 $
b0 #
b0 "
b0 !
$end
#10
b110 )
b1 "
b1 %
b1 $
#20
b110 )
b10 "
b10 %
b10 $
#30
b110 )
b11 "
b11 %
b11 $
#40
b110 )
b100 "
b100 %
b100 $
#50
b110 )
b101 "
b101 %
b101 $
#60
b110 )
b110 "
b110 %
b110 $
#70
b110 )
b111 "
b111 %
b111 $
#80
b110 )
b1000 "
b1000 %
b1000 $
#90
b110 )
b1001 "
b1001 %
b1001 $
#100
b110 )
b1010 "
b1010 %
b1010 $
#110
b110 )
b1011 "
b1011 %
b1011 $
#120
b110 )
b1100 "
b1100 %
b1100 $
#130
b110 )
b1101 "
b1101 %
b1101 $
#140
b110 )
b1110 "
b1110 %
b1110 $
#150
b110 )
b1111 "
b1111 %
b1111 $
#160
b110 )
b10000 "
b10000 %
b10000 $
#170
b110 )
b10001 "
b10001 %
b10001 $
#180
b110 )
b10010 "
b10010 %
b10010 $
#190
b110 )
b10011 "
b10011 %
b10011 $
#200
b110 )
b10100 "
b10100 %
b10100 $
#210
b110 )
b10101 "
b10101 %
b10101 $
#220
b110 )
b10110 "
b10110 %
b10110 $
#230
b110 )
b10111 "
b10111 %
b10111 $
#240
b110 )
b11000 "
b11000 %
b11000 $
#250
b110 )
b11001 "
b11001 %
b11001 $
#260
b110 )
b11010 "
b11010 %
b11010 $
#270
b110 )
b11011 "
b11011 %
b11011 $
#280
b110 )
b11100 "
b11100 %
b11100 $
#290
b110 )
b11101 "
b11101 %
b11101 $
#300
b110 )
b11110 "
b11110 %
b11110 $
#310
b110 )
b11111 "
b11111 %
b11111 $
#320
b110 )
b100000 "
b100000 %
b100000 $
#330
b110 )
b100001 "
b100001 %
b100001 $
#340
b110 )
b100010 "
b100010 %
b100010 $
#350
b110 )
b100011 "
b100011 %
b100011 $
#360
b110 )
b100100 "
b100100 %
b100100 $
#370
b110 )
b100101 "
b100101 %
b100101 $
#380
b110 )
b100110 "
b100110 %
b100110 $
#390
b110 )
b100111 "
b100111 %
b100111 $
#400
b110 )
b101000 "
b101000 %
b101000 $
#410
b110 )
b101001 "
b101001 %
b101001 $
#420
b110 )
b101010 "
b101010 %
b101010 $
#430
b110 )
b101011 "
b101011 %
b101011 $
#440
b110 )
b101100 "
b101100 %
b101100 $
#450
b110 )
b101101 "
b101101 %
b101101 $
#460
b110 )
b101110 "
b101110 %
b101110 $
#470
b110 )
b101111 "
b101111 %
b101111 $
#480
b110 )
b110000 "
b110000 %
b110000 $
#490
b110 )
b110001 "
b110001 %
b110001 $
#500
b110 )
b110010 "
b110010 %
b110010 $
#510
b110 )
b110011 "
b110011 %
b110011 $
#520
b110 )
b110100 "
b110100 %
b110100 $
#530
b110 )
b110101 "
b110101 %
b110101 $
#540
b110 )
b110110 "
b110110 %
b110110 $
#550
b110 )
b110111 "
b110111 %
b110111 $
#560
b110 )
b111000 "
b111000 %
b111000 $
#570
b110 )
b111001 "
b111001 %
b111001 $
#580
b110 )
b111010 "
b111010 %
b111010 $
#590
b110 )
b111011 "
b111011 %
b111011 $
#600
b110 )
b111100 "
b111100 %
b111100 $
#610
b110 )
b111101 "
b111101 %
b111101 $
#620
b110 )
b111110 "
b111110 %
b111110 $
#630
b110 )
b111111 "
b111111 %
b111111 $
#640
b110 )
b1 #
b1 '
b0 "
b0 %
b1000000 $
#650
b1 !
b1 &
b1 (
b110 )
b1 "
b1 %
b1000001 $
#660
b110 )
b10 !
b10 &
b10 (
b10 "
b10 %
b1000010 $
#670
b110 )
b11 !
b11 &
b11 (
b11 "
b11 %
b1000011 $
#680
b110 )
b100 !
b100 &
b100 (
b100 "
b100 %
b1000100 $
#690
b110 )
b101 !
b101 &
b101 (
b101 "
b101 %
b1000101 $
#700
b110 )
b110 !
b110 &
b110 (
b110 "
b110 %
b1000110 $
#710
b110 )
b111 !
b111 &
b111 (
b111 "
b111 %
b1000111 $
#720
b110 )
b1000 !
b1000 &
b1000 (
b1000 "
b1000 %
b1001000 $
#730
b110 )
b1001 !
b1001 &
b1001 (
b1001 "
b1001 %
b1001001 $
#740
b110 )
b1010 !
b1010 &
b1010 (
b1010 "
b1010 %
b1001010 $
#750
b110 )
b1011 !
b1011 &
b1011 (
b1011 "
b1011 %
b1001011 $
#760
b110 )
b1100 !
b1100 &
b1100 (
b1100 "
b1100 %
b1001100 $
#770
b110 )
b1101 !
b1101 &
b1101 (
b1101 "
b1101 %
b1001101 $
#780
b110 )
b1110 !
b1110 &
b1110 (
b1110 "
b1110 %
b1001110 $
#790
b110 )
b1111 !
b1111 &
b1111 (
b1111 "
b1111 %
b1001111 $
#800
b110 )
b10000 !
b10000 &
b10000 (
b10000 "
b10000 %
b1010000 $
#810
b110 )
b10001 !
b10001 &
b10001 (
b10001 "
b10001 %
b1010001 $
#820
b110 )
b10010 !
b10010 &
b10010 (
b10010 "
b10010 %
b1010010 $
#830
b110 )
b10011 !
b10011 &
b10011 (
b10011 "
b10011 %
b1010011 $
#840
b110 )
b10100 !
b10100 &
b10100 (
b10100 "
b10100 %
b1010100 $
#850
b110 )
b10101 !
b10101 &
b10101 (
b10101 "
b10101 %
b1010101 $
#860
b110 )
b10110 !
b10110 &
b10110 (
b10110 "
b10110 %
b1010110 $
#870
b110 )
b10111 !
b10111 &
b10111 (
b10111 "
b10111 %
b1010111 $
#880
b110 )
b11000 !
b11000 &
b11000 (
b11000 "
b11000 %
b1011000 $
#890
b110 )
b11001 !
b11001 &
b11001 (
b11001 "
b11001 %
b1011001 $
#900
b110 )
b11010 !
b11010 &
b11010 (
b11010 "
b11010 %
b1011010 $
#910
b110 )
b11011 !
b11011 &
b11011 (
b11011 "
b11011 %
b1011011 $
#920
b110 )
b11100 !
b11100 &
b11100 (
b11100 "
b11100 %
b1011100 $
#930
b110 )
b11101 !
b11101 &
b11101 (
b11101 "
b11101 %
b1011101 $
#940
b110 )
b11110 !
b11110 &
b11110 (
b11110 "
b11110 %
b1011110 $
#950
b110 )
b11111 !
b11111 &
b11111 (
b11111 "
b11111 %
b1011111 $
#960
b110 )
b100000 !
b100000 &
b100000 (
b100000 "
b100000 %
b1100000 $
#970
b110 )
b100001 !
b100001 &
b100001 (
b100001 "
b100001 %
b1100001 $
#980
b110 )
b100010 !
b100010 &
b100010 (
b100010 "
b100010 %
b1100010 $
#990
b110 )
b100011 !
b100011 &
b100011 (
b100011 "
b100011 %
b1100011 $
#1000
b110 )
b100100 !
b100100 &
b100100 (
b100100 "
b100100 %
b1100100 $
#1010
b110 )
b100101 !
b100101 &
b100101 (
b100101 "
b100101 %
b1100101 $
#1020
b110 )
b100110 !
b100110 &
b100110 (
b100110 "
b100110 %
b1100110 $
#1030
b110 )
b100111 !
b100111 &
b100111 (
b100111 "
b100111 %
b1100111 $
#1040
b110 )
b101000 !
b101000 &
b101000 (
b101000 "
b101000 %
b1101000 $
#1050
b110 )
b101001 !
b101001 &
b101001 (
b101001 "
b101001 %
b1101001 $
#1060
b110 )
b101010 !
b101010 &
b101010 (
b101010 "
b101010 %
b1101010 $
#1070
b110 )
b101011 !
b101011 &
b101011 (
b101011 "
b101011 %
b1101011 $
#1080
b110 )
b101100 !
b101100 &
b101100 (
b101100 "
b101100 %
b1101100 $
#1090
b110 )
b101101 !
b101101 &
b101101 (
b101101 "
b101101 %
b1101101 $
#1100
b110 )
b101110 !
b101110 &
b101110 (
b101110 "
b101110 %
b1101110 $
#1110
b110 )
b101111 !
b101111 &
b101111 (
b101111 "
b101111 %
b1101111 $
#1120
b110 )
b110000 !
b110000 &
b110000 (
b110000 "
b110000 %
b1110000 $
#1130
b110 )
b110001 !
b110001 &
b110001 (
b110001 "
b110001 %
b1110001 $
#1140
b110 )
b110010 !
b110010 &
b110010 (
b110010 "
b110010 %
b1110010 $
#1150
b110 )
b110011 !
b110011 &
b110011 (
b110011 "
b110011 %
b1110011 $
#1160
b110 )
b110100 !
b110100 &
b110100 (
b110100 "
b110100 %
b1110100 $
#1170
b110 )
b110101 !
b110101 &
b110101 (
b110101 "
b110101 %
b1110101 $
#1180
b110 )
b110110 !
b110110 &
b110110 (
b110110 "
b110110 %
b1110110 $
#1190
b110 )
b110111 !
b110111 &
b110111 (
b110111 "
b110111 %
b1110111 $
#1200
b110 )
b111000 !
b111000 &
b111000 (
b111000 "
b111000 %
b1111000 $
#1210
b110 )
b111001 !
b111001 &
b111001 (
b111001 "
b111001 %
b1111001 $
#1220
b110 )
b111010 !
b111010 &
b111010 (
b111010 "
b111010 %
b1111010 $
#1230
b110 )
b111011 !
b111011 &
b111011 (
b111011 "
b111011 %
b1111011 $
#1240
b110 )
b111100 !
b111100 &
b111100 (
b111100 "
b111100 %
b1111100 $
#1250
b110 )
b111101 !
b111101 &
b111101 (
b111101 "
b111101 %
b1111101 $
#1260
b110 )
b111110 !
b111110 &
b111110 (
b111110 "
b111110 %
b1111110 $
#1270
b110 )
b111111 !
b111111 &
b111111 (
b111111 "
b111111 %
b1111111 $
#1280
b110 )
b0 !
b0 &
b0 (
b10 #
b10 '
b0 "
b0 %
b10000000 $
#1290
b10 !
b10 &
b10 (
b110 )
b1 "
b1 %
b10000001 $
#1300
b110 )
b100 !
b100 &
b100 (
b10 "
b10 %
b10000010 $
#1310
b110 )
b110 !
b110 &
b110 (
b11 "
b11 %
b10000011 $
#1320
b110 )
b1000 !
b1000 &
b1000 (
b100 "
b100 %
b10000100 $
#1330
b110 )
b1010 !
b1010 &
b1010 (
b101 "
b101 %
b10000101 $
#1340
b110 )
b1100 !
b1100 &
b1100 (
b110 "
b110 %
b10000110 $
#1350
b110 )
b1110 !
b1110 &
b1110 (
b111 "
b111 %
b10000111 $
#1360
b110 )
b10000 !
b10000 &
b10000 (
b1000 "
b1000 %
b10001000 $
#1370
b110 )
b10010 !
b10010 &
b10010 (
b1001 "
b1001 %
b10001001 $
#1380
b110 )
b10100 !
b10100 &
b10100 (
b1010 "
b1010 %
b10001010 $
#1390
b110 )
b10110 !
b10110 &
b10110 (
b1011 "
b1011 %
b10001011 $
#1400
b110 )
b11000 !
b11000 &
b11000 (
b1100 "
b1100 %
b10001100 $
#1410
b110 )
b11010 !
b11010 &
b11010 (
b1101 "
b1101 %
b10001101 $
#1420
b110 )
b11100 !
b11100 &
b11100 (
b1110 "
b1110 %
b10001110 $
#1430
b110 )
b11110 !
b11110 &
b11110 (
b1111 "
b1111 %
b10001111 $
#1440
b110 )
b100000 !
b100000 &
b100000 (
b10000 "
b10000 %
b10010000 $
#1450
b110 )
b100010 !
b100010 &
b100010 (
b10001 "
b10001 %
b10010001 $
#1460
b110 )
b100100 !
b100100 &
b100100 (
b10010 "
b10010 %
b10010010 $
#1470
b110 )
b100110 !
b100110 &
b100110 (
b10011 "
b10011 %
b10010011 $
#1480
b110 )
b101000 !
b101000 &
b101000 (
b10100 "
b10100 %
b10010100 $
#1490
b110 )
b101010 !
b101010 &
b101010 (
b10101 "
b10101 %
b10010101 $
#1500
b110 )
b101100 !
b101100 &
b101100 (
b10110 "
b10110 %
b10010110 $
#1510
b110 )
b101110 !
b101110 &
b101110 (
b10111 "
b10111 %
b10010111 $
#1520
b110 )
b110000 !
b110000 &
b110000 (
b11000 "
b11000 %
b10011000 $
#1530
b110 )
b110010 !
b110010 &
b110010 (
b11001 "
b11001 %
b10011001 $
#1540
b110 )
b110100 !
b110100 &
b110100 (
b11010 "
b11010 %
b10011010 $
#1550
b110 )
b110110 !
b110110 &
b110110 (
b11011 "
b11011 %
b10011011 $
#1560
b110 )
b111000 !
b111000 &
b111000 (
b11100 "
b11100 %
b10011100 $
#1570
b110 )
b111010 !
b111010 &
b111010 (
b11101 "
b11101 %
b10011101 $
#1580
b110 )
b111100 !
b111100 &
b111100 (
b11110 "
b11110 %
b10011110 $
#1590
b110 )
b111110 !
b111110 &
b111110 (
b11111 "
b11111 %
b10011111 $
#1600
b110 )
b1000000 !
b1000000 &
b1000000 (
b100000 "
b100000 %
b10100000 $
#1610
b110 )
b1000010 !
b1000010 &
b1000010 (
b100001 "
b100001 %
b10100001 $
#1620
b110 )
b1000100 !
b1000100 &
b1000100 (
b100010 "
b100010 %
b10100010 $
#1630
b110 )
b1000110 !
b1000110 &
b1000110 (
b100011 "
b100011 %
b10100011 $
#1640
b110 )
b1001000 !
b1001000 &
b1001000 (
b100100 "
b100100 %
b10100100 $
#1650
b110 )
b1001010 !
b1001010 &
b1001010 (
b100101 "
b100101 %
b10100101 $
#1660
b110 )
b1001100 !
b1001100 &
b1001100 (
b100110 "
b100110 %
b10100110 $
#1670
b110 )
b1001110 !
b1001110 &
b1001110 (
b100111 "
b100111 %
b10100111 $
#1680
b110 )
b1010000 !
b1010000 &
b1010000 (
b101000 "
b101000 %
b10101000 $
#1690
b110 )
b1010010 !
b1010010 &
b1010010 (
b101001 "
b101001 %
b10101001 $
#1700
b110 )
b1010100 !
b1010100 &
b1010100 (
b101010 "
b101010 %
b10101010 $
#1710
b110 )
b1010110 !
b1010110 &
b1010110 (
b101011 "
b101011 %
b10101011 $
#1720
b110 )
b1011000 !
b1011000 &
b1011000 (
b101100 "
b101100 %
b10101100 $
#1730
b110 )
b1011010 !
b1011010 &
b1011010 (
b101101 "
b101101 %
b10101101 $
#1740
b110 )
b1011100 !
b1011100 &
b1011100 (
b101110 "
b101110 %
b10101110 $
#1750
b110 )
b1011110 !
b1011110 &
b1011110 (
b101111 "
b101111 %
b10101111 $
#1760
b110 )
b1100000 !
b1100000 &
b1100000 (
b110000 "
b110000 %
b10110000 $
#1770
b110 )
b1100010 !
b1100010 &
b1100010 (
b110001 "
b110001 %
b10110001 $
#1780
b110 )
b1100100 !
b1100100 &
b1100100 (
b110010 "
b110010 %
b10110010 $
#1790
b110 )
b1100110 !
b1100110 &
b1100110 (
b110011 "
b110011 %
b10110011 $
#1800
b110 )
b1101000 !
b1101000 &
b1101000 (
b110100 "
b110100 %
b10110100 $
#1810
b110 )
b1101010 !
b1101010 &
b1101010 (
b110101 "
b110101 %
b10110101 $
#1820
b110 )
b1101100 !
b1101100 &
b1101100 (
b110110 "
b110110 %
b10110110 $
#1830
b110 )
b1101110 !
b1101110 &
b1101110 (
b110111 "
b110111 %
b10110111 $
#1840
b110 )
b1110000 !
b1110000 &
b1110000 (
b111000 "
b111000 %
b10111000 $
#1850
b110 )
b1110010 !
b1110010 &
b1110010 (
b111001 "
b111001 %
b10111001 $
#1860
b110 )
b1110100 !
b1110100 &
b1110100 (
b111010 "
b111010 %
b10111010 $
#1870
b110 )
b1110110 !
b1110110 &
b1110110 (
b111011 "
b111011 %
b10111011 $
#1880
b110 )
b1111000 !
b1111000 &
b1111000 (
b111100 "
b111100 %
b10111100 $
#1890
b110 )
b1111010 !
b1111010 &
b1111010 (
b111101 "
b111101 %
b10111101 $
#1900
b110 )
b1111100 !
b1111100 &
b1111100 (
b111110 "
b111110 %
b10111110 $
#1910
b110 )
b1111110 !
b1111110 &
b1111110 (
b111111 "
b111111 %
b10111111 $
#1920
b110 )
b0 !
b0 &
b0 (
b11 #
b11 '
b0 "
b0 %
b11000000 $
#1930
b11 !
b11 &
b11 (
b110 )
b1 "
b1 %
b11000001 $
#1940
b110 )
b110 !
b110 &
b110 (
b10 "
b10 %
b11000010 $
#1950
b110 )
b1001 !
b1001 &
b1001 (
b11 "
b11 %
b11000011 $
#1960
b110 )
b1100 !
b1100 &
b1100 (
b100 "
b100 %
b11000100 $
#1970
b110 )
b1111 !
b1111 &
b1111 (
b101 "
b101 %
b11000101 $
#1980
b110 )
b10010 !
b10010 &
b10010 (
b110 "
b110 %
b11000110 $
#1990
b110 )
b10101 !
b10101 &
b10101 (
b111 "
b111 %
b11000111 $
#2000
b110 )
b11000 !
b11000 &
b11000 (
b1000 "
b1000 %
b11001000 $
#2010
b110 )
b11011 !
b11011 &
b11011 (
b1001 "
b1001 %
b11001001 $
#2020
b110 )
b11110 !
b11110 &
b11110 (
b1010 "
b1010 %
b11001010 $
#2030
b110 )
b100001 !
b100001 &
b100001 (
b1011 "
b1011 %
b11001011 $
#2040
b110 )
b100100 !
b100100 &
b100100 (
b1100 "
b1100 %
b11001100 $
#2050
b110 )
b100111 !
b100111 &
b100111 (
b1101 "
b1101 %
b11001101 $
#2060
b110 )
b101010 !
b101010 &
b101010 (
b1110 "
b1110 %
b11001110 $
#2070
b110 )
b101101 !
b101101 &
b101101 (
b1111 "
b1111 %
b11001111 $
#2080
b110 )
b110000 !
b110000 &
b110000 (
b10000 "
b10000 %
b11010000 $
#2090
b110 )
b110011 !
b110011 &
b110011 (
b10001 "
b10001 %
b11010001 $
#2100
b110 )
b110110 !
b110110 &
b110110 (
b10010 "
b10010 %
b11010010 $
#2110
b110 )
b111001 !
b111001 &
b111001 (
b10011 "
b10011 %
b11010011 $
#2120
b110 )
b111100 !
b111100 &
b111100 (
b10100 "
b10100 %
b11010100 $
#2130
b110 )
b111111 !
b111111 &
b111111 (
b10101 "
b10101 %
b11010101 $
#2140
b110 )
b1000010 !
b1000010 &
b1000010 (
b10110 "
b10110 %
b11010110 $
#2150
b110 )
b1000101 !
b1000101 &
b1000101 (
b10111 "
b10111 %
b11010111 $
#2160
b110 )
b1001000 !
b1001000 &
b1001000 (
b11000 "
b11000 %
b11011000 $
#2170
b110 )
b1001011 !
b1001011 &
b1001011 (
b11001 "
b11001 %
b11011001 $
#2180
b110 )
b1001110 !
b1001110 &
b1001110 (
b11010 "
b11010 %
b11011010 $
#2190
b110 )
b1010001 !
b1010001 &
b1010001 (
b11011 "
b11011 %
b11011011 $
#2200
b110 )
b1010100 !
b1010100 &
b1010100 (
b11100 "
b11100 %
b11011100 $
#2210
b110 )
b1010111 !
b1010111 &
b1010111 (
b11101 "
b11101 %
b11011101 $
#2220
b110 )
b1011010 !
b1011010 &
b1011010 (
b11110 "
b11110 %
b11011110 $
#2230
b110 )
b1011101 !
b1011101 &
b1011101 (
b11111 "
b11111 %
b11011111 $
#2240
b110 )
b1100000 !
b1100000 &
b1100000 (
b100000 "
b100000 %
b11100000 $
#2250
b110 )
b1100011 !
b1100011 &
b1100011 (
b100001 "
b100001 %
b11100001 $
#2260
b110 )
b1100110 !
b1100110 &
b1100110 (
b100010 "
b100010 %
b11100010 $
#2270
b110 )
b1101001 !
b1101001 &
b1101001 (
b100011 "
b100011 %
b11100011 $
#2280
b110 )
b1101100 !
b1101100 &
b1101100 (
b100100 "
b100100 %
b11100100 $
#2290
b110 )
b1101111 !
b1101111 &
b1101111 (
b100101 "
b100101 %
b11100101 $
#2300
b110 )
b1110010 !
b1110010 &
b1110010 (
b100110 "
b100110 %
b11100110 $
#2310
b110 )
b1110101 !
b1110101 &
b1110101 (
b100111 "
b100111 %
b11100111 $
#2320
b110 )
b1111000 !
b1111000 &
b1111000 (
b101000 "
b101000 %
b11101000 $
#2330
b110 )
b1111011 !
b1111011 &
b1111011 (
b101001 "
b101001 %
b11101001 $
#2340
b110 )
b1111110 !
b1111110 &
b1111110 (
b101010 "
b101010 %
b11101010 $
#2350
b110 )
b10000001 !
b10000001 &
b10000001 (
b101011 "
b101011 %
b11101011 $
#2360
b110 )
b10000100 !
b10000100 &
b10000100 (
b101100 "
b101100 %
b11101100 $
#2370
b110 )
b10000111 !
b10000111 &
b10000111 (
b101101 "
b101101 %
b11101101 $
#2380
b110 )
b10001010 !
b10001010 &
b10001010 (
b101110 "
b101110 %
b11101110 $
#2390
b110 )
b10001101 !
b10001101 &
b10001101 (
b101111 "
b101111 %
b11101111 $
#2400
b110 )
b10010000 !
b10010000 &
b10010000 (
b110000 "
b110000 %
b11110000 $
#2410
b110 )
b10010011 !
b10010011 &
b10010011 (
b110001 "
b110001 %
b11110001 $
#2420
b110 )
b10010110 !
b10010110 &
b10010110 (
b110010 "
b110010 %
b11110010 $
#2430
b110 )
b10011001 !
b10011001 &
b10011001 (
b110011 "
b110011 %
b11110011 $
#2440
b110 )
b10011100 !
b10011100 &
b10011100 (
b110100 "
b110100 %
b11110100 $
#2450
b110 )
b10011111 !
b10011111 &
b10011111 (
b110101 "
b110101 %
b11110101 $
#2460
b110 )
b10100010 !
b10100010 &
b10100010 (
b110110 "
b110110 %
b11110110 $
#2470
b110 )
b10100101 !
b10100101 &
b10100101 (
b110111 "
b110111 %
b11110111 $
#2480
b110 )
b10101000 !
b10101000 &
b10101000 (
b111000 "
b111000 %
b11111000 $
#2490
b110 )
b10101011 !
b10101011 &
b10101011 (
b111001 "
b111001 %
b11111001 $
#2500
b110 )
b10101110 !
b10101110 &
b10101110 (
b111010 "
b111010 %
b11111010 $
#2510
b110 )
b10110001 !
b10110001 &
b10110001 (
b111011 "
b111011 %
b11111011 $
#2520
b110 )
b10110100 !
b10110100 &
b10110100 (
b111100 "
b111100 %
b11111100 $
#2530
b110 )
b10110111 !
b10110111 &
b10110111 (
b111101 "
b111101 %
b11111101 $
#2540
b110 )
b10111010 !
b10111010 &
b10111010 (
b111110 "
b111110 %
b11111110 $
#2550
b110 )
b10111101 !
b10111101 &
b10111101 (
b111111 "
b111111 %
b11111111 $
#2560
b110 )
b0 !
b0 &
b0 (
b100 #
b100 '
b0 "
b0 %
b100000000 $
#2570
b100 !
b100 &
b100 (
b110 )
b1 "
b1 %
b100000001 $
#2580
b110 )
b1000 !
b1000 &
b1000 (
b10 "
b10 %
b100000010 $
#2590
b110 )
b1100 !
b1100 &
b1100 (
b11 "
b11 %
b100000011 $
#2600
b110 )
b10000 !
b10000 &
b10000 (
b100 "
b100 %
b100000100 $
#2610
b110 )
b10100 !
b10100 &
b10100 (
b101 "
b101 %
b100000101 $
#2620
b110 )
b11000 !
b11000 &
b11000 (
b110 "
b110 %
b100000110 $
#2630
b110 )
b11100 !
b11100 &
b11100 (
b111 "
b111 %
b100000111 $
#2640
b110 )
b100000 !
b100000 &
b100000 (
b1000 "
b1000 %
b100001000 $
#2650
b110 )
b100100 !
b100100 &
b100100 (
b1001 "
b1001 %
b100001001 $
#2660
b110 )
b101000 !
b101000 &
b101000 (
b1010 "
b1010 %
b100001010 $
#2670
b110 )
b101100 !
b101100 &
b101100 (
b1011 "
b1011 %
b100001011 $
#2680
b110 )
b110000 !
b110000 &
b110000 (
b1100 "
b1100 %
b100001100 $
#2690
b110 )
b110100 !
b110100 &
b110100 (
b1101 "
b1101 %
b100001101 $
#2700
b110 )
b111000 !
b111000 &
b111000 (
b1110 "
b1110 %
b100001110 $
#2710
b110 )
b111100 !
b111100 &
b111100 (
b1111 "
b1111 %
b100001111 $
#2720
b110 )
b1000000 !
b1000000 &
b1000000 (
b10000 "
b10000 %
b100010000 $
#2730
b110 )
b1000100 !
b1000100 &
b1000100 (
b10001 "
b10001 %
b100010001 $
#2740
b110 )
b1001000 !
b1001000 &
b1001000 (
b10010 "
b10010 %
b100010010 $
#2750
b110 )
b1001100 !
b1001100 &
b1001100 (
b10011 "
b10011 %
b100010011 $
#2760
b110 )
b1010000 !
b1010000 &
b1010000 (
b10100 "
b10100 %
b100010100 $
#2770
b110 )
b1010100 !
b1010100 &
b1010100 (
b10101 "
b10101 %
b100010101 $
#2780
b110 )
b1011000 !
b1011000 &
b1011000 (
b10110 "
b10110 %
b100010110 $
#2790
b110 )
b1011100 !
b1011100 &
b1011100 (
b10111 "
b10111 %
b100010111 $
#2800
b110 )
b1100000 !
b1100000 &
b1100000 (
b11000 "
b11000 %
b100011000 $
#2810
b110 )
b1100100 !
b1100100 &
b1100100 (
b11001 "
b11001 %
b100011001 $
#2820
b110 )
b1101000 !
b1101000 &
b1101000 (
b11010 "
b11010 %
b100011010 $
#2830
b110 )
b1101100 !
b1101100 &
b1101100 (
b11011 "
b11011 %
b100011011 $
#2840
b110 )
b1110000 !
b1110000 &
b1110000 (
b11100 "
b11100 %
b100011100 $
#2850
b110 )
b1110100 !
b1110100 &
b1110100 (
b11101 "
b11101 %
b100011101 $
#2860
b110 )
b1111000 !
b1111000 &
b1111000 (
b11110 "
b11110 %
b100011110 $
#2870
b110 )
b1111100 !
b1111100 &
b1111100 (
b11111 "
b11111 %
b100011111 $
#2880
b110 )
b10000000 !
b10000000 &
b10000000 (
b100000 "
b100000 %
b100100000 $
#2890
b110 )
b10000100 !
b10000100 &
b10000100 (
b100001 "
b100001 %
b100100001 $
#2900
b110 )
b10001000 !
b10001000 &
b10001000 (
b100010 "
b100010 %
b100100010 $
#2910
b110 )
b10001100 !
b10001100 &
b10001100 (
b100011 "
b100011 %
b100100011 $
#2920
b110 )
b10010000 !
b10010000 &
b10010000 (
b100100 "
b100100 %
b100100100 $
#2930
b110 )
b10010100 !
b10010100 &
b10010100 (
b100101 "
b100101 %
b100100101 $
#2940
b110 )
b10011000 !
b10011000 &
b10011000 (
b100110 "
b100110 %
b100100110 $
#2950
b110 )
b10011100 !
b10011100 &
b10011100 (
b100111 "
b100111 %
b100100111 $
#2960
b110 )
b10100000 !
b10100000 &
b10100000 (
b101000 "
b101000 %
b100101000 $
#2970
b110 )
b10100100 !
b10100100 &
b10100100 (
b101001 "
b101001 %
b100101001 $
#2980
b110 )
b10101000 !
b10101000 &
b10101000 (
b101010 "
b101010 %
b100101010 $
#2990
b110 )
b10101100 !
b10101100 &
b10101100 (
b101011 "
b101011 %
b100101011 $
#3000
b110 )
b10110000 !
b10110000 &
b10110000 (
b101100 "
b101100 %
b100101100 $
#3010
b110 )
b10110100 !
b10110100 &
b10110100 (
b101101 "
b101101 %
b100101101 $
#3020
b110 )
b10111000 !
b10111000 &
b10111000 (
b101110 "
b101110 %
b100101110 $
#3030
b110 )
b10111100 !
b10111100 &
b10111100 (
b101111 "
b101111 %
b100101111 $
#3040
b110 )
b11000000 !
b11000000 &
b11000000 (
b110000 "
b110000 %
b100110000 $
#3050
b110 )
b11000100 !
b11000100 &
b11000100 (
b110001 "
b110001 %
b100110001 $
#3060
b110 )
b11001000 !
b11001000 &
b11001000 (
b110010 "
b110010 %
b100110010 $
#3070
b110 )
b11001100 !
b11001100 &
b11001100 (
b110011 "
b110011 %
b100110011 $
#3080
b110 )
b11010000 !
b11010000 &
b11010000 (
b110100 "
b110100 %
b100110100 $
#3090
b110 )
b11010100 !
b11010100 &
b11010100 (
b110101 "
b110101 %
b100110101 $
#3100
b110 )
b11011000 !
b11011000 &
b11011000 (
b110110 "
b110110 %
b100110110 $
#3110
b110 )
b11011100 !
b11011100 &
b11011100 (
b110111 "
b110111 %
b100110111 $
#3120
b110 )
b11100000 !
b11100000 &
b11100000 (
b111000 "
b111000 %
b100111000 $
#3130
b110 )
b11100100 !
b11100100 &
b11100100 (
b111001 "
b111001 %
b100111001 $
#3140
b110 )
b11101000 !
b11101000 &
b11101000 (
b111010 "
b111010 %
b100111010 $
#3150
b110 )
b11101100 !
b11101100 &
b11101100 (
b111011 "
b111011 %
b100111011 $
#3160
b110 )
b11110000 !
b11110000 &
b11110000 (
b111100 "
b111100 %
b100111100 $
#3170
b110 )
b11110100 !
b11110100 &
b11110100 (
b111101 "
b111101 %
b100111101 $
#3180
b110 )
b11111000 !
b11111000 &
b11111000 (
b111110 "
b111110 %
b100111110 $
#3190
b110 )
b11111100 !
b11111100 &
b11111100 (
b111111 "
b111111 %
b100111111 $
#3200
b110 )
b0 !
b0 &
b0 (
b101 #
b101 '
b0 "
b0 %
b101000000 $
#3210
b101 !
b101 &
b101 (
b110 )
b1 "
b1 %
b101000001 $
#3220
b110 )
b1010 !
b1010 &
b1010 (
b10 "
b10 %
b101000010 $
#3230
b110 )
b1111 !
b1111 &
b1111 (
b11 "
b11 %
b101000011 $
