vvc/moore1.v
module moore1(clock, reset_, x, z);
input clock, reset_, x;
output z;
// 宣告狀態
parameter [1:0] S0 = 2'b00, S1 = 2'b01, S2 = 2'b11, S3 = 2'b10;
// 宣告狀態變數目前狀態
reg [1:0] curr_state, next_state;
// 狀態變遷(state transition)，下一個狀態
always @(posedge clock)
if(~reset_) next_state <= #1 S0;
else
  case(curr_state)
    S0: if(x==1'b1) next_state <= #1 S1;
        else next_state <= #1 S3;
    S1: if(x==1'b1) next_state <= #1 S2;
        else next_state <= #1 S0;
    S2: if(x==1'b0) next_state <= #1 S1;
    S3: if(x==1'b1) next_state <= #1 S2;
        else next_state <= #1 S2;
  endcase

always @(next_state)
    curr_state <= #1 next_state;

reg z;
// 由目前狀態決定輸出
always @(curr_state or reset_)
    if(~reset_) z <= #1 1'b0;

    else
      case(curr_state)
      S0, S2: z <= #1 1'b0;
      S1, S3: z <= #1 1'b1;
    endcase
endmodule

module test;
reg clock, reset_, x;
wire z;

moore1 U1(clock, reset_, x, z);

always #10
  clock = ~clock;

initial begin
    $dumpfile("vcd/moore1.vcd");
    $dumpvars();
end

initial begin
    #0 clock=0; reset_=0; x=0;
    #15 reset_=1;
    #100 x=1;
    #100 x=0;
    #100 x=1;
    #100 x=0;
    #100 x=1;
    #100 x=0;
    #100 x=1;
    #100 x=0;
    #100 x=1;
    #100 x=0;
    #100 $finish;
end
endmodule;

vcd/moore1.vcd
$date
	Tue Apr  8 16:02:56 2025
$end
$version
	Icarus Verilog
$end
$timescale
	1s
$end
$scope module test $end
$var wire 1 ! z $end
$var reg 1 " clock $end
$var reg 1 # reset_ $end
$var reg 1 $ x $end
$scope module U1 $end
$var wire 1 " clock $end
$var wire 1 # reset_ $end
$var wire 1 $ x $end
$var parameter 2 % S0 $end
$var parameter 2 & S1 $end
$var parameter 2 ' S2 $end
$var parameter 2 ( S3 $end
$var reg 2 ) curr_state [1:0] $end
$var reg 2 * next_state [1:0] $end
$var reg 1 ! z $end
$upscope $end
$upscope $end
$enddefinitions $end
$comment Show the parameter values. $end
$dumpall
b10 (
b11 '
b1 &
b0 %
$end
#0
$dumpvars
bx *
bx )
0$
0#
0"
x!
$end
#1
0!
#10
1"
#11
b0 *
#12
b0 )
#15
1#
#20
0"
#30
1"
#31
b10 *
#32
b10 )
#33
1!
#40
0"
#50
1"
#51
b11 *
#52
b11 )
#53
0!
#60
0"
#70
1"
#71
b1 *
#72
b1 )
#73
1!
#80
0"
#90
1"
#91
b0 *
#92
b0 )
#93
0!
#100
0"
#110
1"
#111
b10 *
#112
b10 )
#113
1!
#115
1$
#120
0"
#130
1"
#131
b11 *
#132
b11 )
#133
0!
#140
0"
#150
1"
#160
0"
#170
1"
#180
0"
#190
1"
#200
0"
#210
1"
#215
0$
#220
0"
#230
1"
#231
b1 *
#232
b1 )
#233
1!
#240
0"
#250
1"
#251
b0 *
#252
b0 )
#253
0!
#260
0"
#270
1"
#271
b10 *
#272
b10 )
#273
1!
#280
0"
#290
1"
#291
b11 *
#292
b11 )
#293
0!
#300
0"
#310
1"
#311
b1 *
#312
b1 )
#313
1!
#315
1$
#320
0"
#330
1"
#331
b11 *
#332
b11 )
#333
0!
#340
0"
#350
1"
#360
0"
#370
1"
#380
0"
#390
1"
#400
0"
#410
1"
#415
0$
#420
0"
#430
1"
#431
b1 *
#432
b1 )
#433
1!
#440
0"
#450
1"
#451
b0 *
#452
b0 )
#453
0!
#460
0"
#470
1"
#471
b10 *
#472
b10 )
#473
1!
#480
0"
#490
1"
#491
b11 *
#492
b11 )
#493
0!
#500
0"
#510
1"
#511
b1 *
#512
b1 )
#513
1!
#515
1$
#520
0"
#530
1"
#531
b11 *
#532
b11 )
#533
0!
#540
0"
#550
1"
#560
0"
#570
1"
#580
0"
#590
1"
#600
0"
#610
1"
#615
0$
#620
0"
#630
1"
#631
b1 *
#632
b1 )
#633
1!
#640
0"
#650
1"
#651
b0 *
#652
b0 )
#653
0!
#660
0"
#670
1"
#671
b10 *
#672
b10 )
#673
1!
#680
0"
#690
1"
#691
b11 *
#692
b11 )
#693
0!
#700
0"
#710
1"
#711
b1 *
#712
b1 )
#713
1!
#715
1$
#720
0"
#730
1"
#731
b11 *
#732
b11 )
#733
0!
#740
0"
#750
1"
#760
0"
#770
1"
#780
0"
#790
1"
#800
0"
#810
1"
#815
0$
#820
0"
#830
1"
#831
b1 *
#832
b1 )
#833
1!
#840
0"
#850
1"
#851
b0 *
#852
b0 )
#853
0!
#860
0"
#870
1"
#871
b10 *
#872
b10 )
#873
1!
#880
0"
#890
1"
#891
b11 *
#892
b11 )
#893
0!
#900
0"
#910
1"
#911
b1 *
#912
b1 )
#913
1!
#915
1$
#920
0"
#930
1"
#931
b11 *
#932
b11 )
#933
0!
#940
0"
#950
1"
#960
0"
#970
1"
#980
0"
#990
1"
#1000
0"
#1010
1"
#1015
0$
#1020
0"
#1030
1"
#1031
b1 *
#1032
b1 )
#1033
1!
#1040
0"
#1050
1"
#1051
b0 *
#1052
b0 )
#1053
0!
#1060
0"
#1070
1"
#1071
b10 *
#1072
b10 )
#1073
1!
#1080
0"
#1090
1"
#1091
b11 *
#1092
b11 )
#1093
0!
#1100
0"
#1110
1"
#1111
b1 *
#1112
b1 )
#1113
1!
