vvc/rom.v
module rom16(addr, data);
input [3:0] addr;
output reg [3:0] data;

always @(*) begin
    case(addr)
        4'd0: data = #1 4'd0;
        4'd1: data = #1 4'd1;
        4'd2: data = #1 4'd2;
        4'd3: data = #1 4'd3;
        4'd4: data = #1 4'd4;
        4'd5: data = #1 4'd5;
        4'd6: data = #1 4'd6;
        4'd7: data = #1 4'd7;
        4'd8: data = #1 4'd8;
        4'd9: data = #1 4'd9;
        4'd10: data = #1 4'd10;
        4'd11: data = #1 4'd11;
        4'd12: data = #1 4'd12;
        4'd13: data = #1 4'd13;
        4'd14: data = #1 4'd14;
        4'd15: data = #1 4'd15;
    endcase
end
endmodule

module test;
reg [3:0] addr;
wire [3:0] data;
integer i;

rom16 U1(addr, data);

initial begin
    $dumpfile("vcd/rom.vcd");
    $dumpvars();
end

initial begin
    for(i=0; i<16; i=i+1) begin
        addr = i;
        #10;
    end
end

always @(*) begin
    $display("%d ns, addr = %d, rom data = %d", $time, addr, data);
end
endmodule

vcd/rom.vcd
$date
	Tue Apr 29 16:31:42 2025
$end
$version
	Icarus Verilog
$end
$timescale
	1s
$end
$scope module test $end
$var wire 4 ! data [3:0] $end
$var reg 4 " addr [3:0] $end
$var integer 32 # i [31:0] $end
$scope module U1 $end
$var wire 4 $ addr [3:0] $end
$var reg 4 % data [3:0] $end
$upscope $end
$upscope $end
$enddefinitions $end
$comment Show the parameter values. $end
$dumpall
$end
#0
$dumpvars
bx %
b0 $
b0 #
b0 "
bx !
$end
#1
b0 !
b0 %
#10
b1 "
b1 $
b1 #
#11
b1 !
b1 %
#20
b10 "
b10 $
b10 #
#21
b10 !
b10 %
#30
b11 "
b11 $
b11 #
#31
b11 !
b11 %
#40
b100 "
b100 $
b100 #
#41
b100 !
b100 %
#50
b101 "
b101 $
b101 #
#51
b101 !
b101 %
#60
b110 "
b110 $
b110 #
#61
b110 !
b110 %
#70
b111 "
b111 $
b111 #
#71
b111 !
b111 %
#80
b1000 "
b1000 $
b1000 #
#81
b1000 !
b1000 %
#90
b1001 "
b1001 $
b1001 #
#91
b1001 !
b1001 %
#100
b1010 "
b1010 $
b1010 #
#101
b1010 !
b1010 %
#110
b1011 "
b1011 $
b1011 #
#111
b1011 !
b1011 %
#120
b1100 "
b1100 $
b1100 #
#121
b1100 !
b1100 %
#130
b1101 "
b1101 $
b1101 #
#131
b1101 !
b1101 %
#140
b1110 "
b1110 $
b1110 #
#141
b1110 !
b1110 %
#150
b1111 "
b1111 $
b1111 #
#151
b1111 !
b1111 %
#160
b10000 #
