vvc/traffic_light.v
module traffic_light (
    input clk,
    input rst_n,
    output reg R1, Y1, G1,  // 橫向
    output reg R2, Y2, G2   // 直向
);

    // 狀態定義
    parameter S0 = 2'b00, // R1=1, R2=0, G2=1
              S1 = 2'b01, // R1=1, R2=0, Y2=1
              S2 = 2'b10, // R1=0, G1=1, R2=1
              S3 = 2'b11; // R1=0, Y1=1, R2=1

    reg [1:0] state;
    reg [6:0] counter;

    // 狀態轉移邏輯
    always @(posedge clk or negedge rst_n) begin
        if (!rst_n) begin
            state <= S0;
            counter <= 0;
        end else begin
            case (state)
                S0: begin
                    if (counter == 7'd99) begin
                        state <= S1;
                        counter <= 0;
                    end else
                        counter <= counter + 1;
                end
                S1: begin
                    if (counter == 7'd19) begin
                        state <= S2;
                        counter <= 0;
                    end else
                        counter <= counter + 1;
                end
                S2: begin
                    if (counter == 7'd99) begin
                        state <= S3;
                        counter <= 0;
                    end else
                        counter <= counter + 1;
                end
                S3: begin
                    if (counter == 7'd19) begin
                        state <= S0;
                        counter <= 0;
                    end else
                        counter <= counter + 1;
                end
            endcase
        end
    end

    // 狀態輸出（Moore）
    always @(*) begin
        // 預設全部關閉
        R1 = 0; Y1 = 0; G1 = 0;
        R2 = 0; Y2 = 0; G2 = 0;

        case (state)
            S0: begin
                R1 = 1; G2 = 1;
            end
            S1: begin
                R1 = 1; Y2 = 1;
            end
            S2: begin
                R2 = 1; G1 = 1;
            end
            S3: begin
                R2 = 1; Y1 = 1;
            end
        endcase
    end

endmodule

vvc/traffic_light_tb.v
`timescale 1ns/1ps

`include "vvc/traffic_light.v"
module traffic_light_tb;

reg clk, rst_n;
wire R1, Y1, G1, R2, Y2, G2;

// 例化被測試模組
traffic_light U1 (
    .clk(clk),
    .rst_n(rst_n),
    .R1(R1), .Y1(Y1), .G1(G1),
    .R2(R2), .Y2(Y2), .G2(G2)
);

// 時脈產生器：20ns 一個週期（10ns 正半週，10ns 負半週）
always #10 clk = ~clk;

// 初始條件與測試流程
initial begin
    $dumpfile("vcd/traffic_light_tb.vcd");  // 波形輸出檔案
    $dumpvars(0, traffic_light_tb);  // 儲存所有變數

    clk = 0;
    rst_n = 0;

    #25 rst_n = 1;  // 釋放 reset，在 25ns 時
end

// 模擬觀察時間：模擬完整兩輪 (S0 → S3 → S0 → S3)
initial begin
    #5000;  // 模擬 5000ns
    $finish;
end

// 顯示輸出變化（可選）
always @(posedge clk) begin
    $display("Time=%dns | R1=%b Y1=%b G1=%b | R2=%b Y2=%b G2=%b",
             $time, R1, Y1, G1, R2, Y2, G2);
end

endmodule

vcd/traffic_light_tb.vcd
$date
	Wed Apr  9 17:35:05 2025
$end
$version
	Icarus Verilog
$end
$timescale
	1ps
$end
$scope module traffic_light_tb $end
$var wire 1 ! Y2 $end
$var wire 1 " Y1 $end
$var wire 1 # R2 $end
$var wire 1 $ R1 $end
$var wire 1 % G2 $end
$var wire 1 & G1 $end
$var reg 1 ' clk $end
$var reg 1 ( rst_n $end
$scope module U1 $end
$var wire 1 ' clk $end
$var wire 1 ( rst_n $end
$var parameter 2 ) S0 $end
$var parameter 2 * S1 $end
$var parameter 2 + S2 $end
$var parameter 2 , S3 $end
$var reg 1 & G1 $end
$var reg 1 % G2 $end
$var reg 1 $ R1 $end
$var reg 1 # R2 $end
$var reg 1 " Y1 $end
$var reg 1 ! Y2 $end
$var reg 7 - counter [6:0] $end
$var reg 2 . state [1:0] $end
$upscope $end
$upscope $end
$enddefinitions $end
$comment Show the parameter values. $end
$dumpall
b11 ,
b10 +
b1 *
b0 )
$end
#0
$dumpvars
b0 .
b0 -
0(
0'
0&
1%
1$
0#
0"
0!
$end
#10000
1'
#20000
0'
#25000
1(
#30000
b1 -
1'
#40000
0'
#50000
b10 -
1'
#60000
0'
#70000
b11 -
1'
#80000
0'
#90000
b100 -
1'
#100000
0'
#110000
b101 -
1'
#120000
0'
#130000
b110 -
1'
#140000
0'
#150000
b111 -
1'
#160000
0'
#170000
b1000 -
1'
#180000
0'
#190000
b1001 -
1'
#200000
0'
#210000
b1010 -
1'
#220000
0'
#230000
b1011 -
1'
#240000
0'
#250000
b1100 -
1'
#260000
0'
#270000
b1101 -
1'
#280000
0'
#290000
b1110 -
1'
#300000
0'
#310000
b1111 -
1'
#320000
0'
#330000
b10000 -
1'
#340000
0'
#350000
b10001 -
1'
#360000
0'
#370000
b10010 -
1'
#380000
0'
#390000
b10011 -
1'
#400000
0'
#410000
b10100 -
1'
#420000
0'
#430000
b10101 -
1'
#440000
0'
#450000
b10110 -
1'
#460000
0'
#470000
b10111 -
1'
#480000
0'
#490000
b11000 -
1'
#500000
0'
#510000
b11001 -
1'
#520000
0'
#530000
b11010 -
1'
#540000
0'
#550000
b11011 -
1'
#560000
0'
#570000
b11100 -
1'
#580000
0'
#590000
b11101 -
1'
#600000
0'
#610000
b11110 -
1'
#620000
0'
#630000
b11111 -
1'
#640000
0'
#650000
b100000 -
1'
#660000
0'
#670000
b100001 -
1'
#680000
0'
#690000
b100010 -
1'
#700000
0'
#710000
b100011 -
1'
#720000
0'
#730000
b100100 -
1'
#740000
0'
#750000
b100101 -
1'
#760000
0'
#770000
b100110 -
1'
#780000
0'
#790000
b100111 -
1'
#800000
0'
#810000
b101000 -
1'
#820000
0'
#830000
b101001 -
1'
#840000
0'
#850000
b101010 -
1'
#860000
0'
#870000
b101011 -
1'
#880000
0'
#890000
b101100 -
1'
#900000
0'
#910000
b101101 -
1'
#920000
0'
#930000
b101110 -
1'
#940000
0'
#950000
b101111 -
1'
#960000
0'
#970000
b110000 -
1'
#980000
0'
#990000
b110001 -
1'
#1000000
0'
#1010000
b110010 -
1'
#1020000
0'
#1030000
b110011 -
1'
#1040000
0'
#1050000
b110100 -
1'
#1060000
0'
#1070000
b110101 -
1'
#1080000
0'
#1090000
b110110 -
1'
#1100000
0'
#1110000
b110111 -
1'
#1120000
0'
#1130000
b111000 -
1'
#1140000
0'
#1150000
b111001 -
1'
#1160000
0'
#1170000
b111010 -
1'
#1180000
0'
#1190000
b111011 -
1'
#1200000
0'
#1210000
b111100 -
1'
#1220000
0'
#1230000
b111101 -
1'
#1240000
0'
#1250000
b111110 -
1'
#1260000
0'
#1270000
b111111 -
1'
#1280000
0'
#1290000
b1000000 -
1'
#1300000
0'
#1310000
b1000001 -
1'
#1320000
0'
#1330000
b1000010 -
1'
#1340000
0'
#1350000
b1000011 -
1'
#1360000
0'
#1370000
b1000100 -
1'
#1380000
0'
#1390000
b1000101 -
1'
#1400000
0'
#1410000
b1000110 -
1'
#1420000
0'
#1430000
b1000111 -
1'
#1440000
0'
#1450000
b1001000 -
1'
#1460000
0'
#1470000
b1001001 -
1'
#1480000
0'
#1490000
b1001010 -
1'
#1500000
0'
#1510000
b1001011 -
1'
#1520000
0'
#1530000
b1001100 -
1'
#1540000
0'
#1550000
b1001101 -
1'
#1560000
0'
#1570000
b1001110 -
1'
#1580000
0'
#1590000
b1001111 -
1'
#1600000
0'
#1610000
b1010000 -
1'
#1620000
0'
#1630000
b1010001 -
1'
#1640000
0'
#1650000
b1010010 -
1'
#1660000
0'
#1670000
b1010011 -
1'
#1680000
0'
#1690000
b1010100 -
1'
#1700000
0'
#1710000
b1010101 -
1'
#1720000
0'
#1730000
b1010110 -
1'
#1740000
0'
#1750000
b1010111 -
1'
#1760000
0'
#1770000
b1011000 -
1'
#1780000
0'
#1790000
b1011001 -
1'
#1800000
0'
#1810000
b1011010 -
1'
#1820000
0'
#1830000
b1011011 -
1'
#1840000
0'
#1850000
b1011100 -
1'
#1860000
0'
#1870000
b1011101 -
1'
#1880000
0'
#1890000
b1011110 -
1'
#1900000
0'
#1910000
b1011111 -
1'
#1920000
0'
#1930000
b1100000 -
1'
#1940000
0'
#1950000
b1100001 -
1'
#1960000
0'
#1970000
b1100010 -
1'
#1980000
0'
#1990000
b1100011 -
1'
#2000000
0'
#2010000
1!
0%
1$
b0 -
b1 .
1'
#2020000
0'
#2030000
b1 -
1'
#2040000
0'
#2050000
b10 -
1'
#2060000
0'
#2070000
b11 -
1'
#2080000
0'
#2090000
b100 -
1'
#2100000
0'
#2110000
b101 -
1'
#2120000
0'
#2130000
b110 -
1'
#2140000
0'
#2150000
b111 -
1'
#2160000
0'
#2170000
b1000 -
1'
#2180000
0'
#2190000
b1001 -
1'
#2200000
0'
#2210000
b1010 -
1'
#2220000
0'
#2230000
b1011 -
1'
#2240000
0'
#2250000
b1100 -
1'
#2260000
0'
#2270000
b1101 -
1'
#2280000
0'
#2290000
b1110 -
1'
#2300000
0'
#2310000
b1111 -
1'
#2320000
0'
#2330000
b10000 -
1'
#2340000
0'
#2350000
b10001 -
1'
#2360000
0'
#2370000
b10010 -
1'
#2380000
0'
#2390000
b10011 -
1'
#2400000
0'
#2410000
1&
1#
0!
0$
b0 -
b10 .
1'
#2420000
0'
#2430000
b1 -
1'
#2440000
0'
#2450000
b10 -
1'
#2460000
0'
#2470000
b11 -
1'
#2480000
0'
#2490000
b100 -
1'
#2500000
0'
#2510000
b101 -
1'
#2520000
0'
#2530000
b110 -
1'
#2540000
0'
#2550000
b111 -
1'
#2560000
0'
#2570000
b1000 -
1'
#2580000
0'
#2590000
b1001 -
1'
#2600000
0'
#2610000
b1010 -
1'
#2620000
0'
#2630000
b1011 -
1'
#2640000
0'
#2650000
b1100 -
1'
#2660000
0'
#2670000
b1101 -
1'
#2680000
0'
#2690000
b1110 -
1'
#2700000
0'
#2710000
b1111 -
1'
#2720000
0'
#2730000
b10000 -
1'
#2740000
0'
#2750000
b10001 -
1'
#2760000
0'
#2770000
b10010 -
1'
#2780000
0'
#2790000
b10011 -
1'
#2800000
0'
#2810000
b10100 -
1'
#2820000
0'
#2830000
b10101 -
1'
#2840000
0'
#2850000
b10110 -
1'
#2860000
0'
#2870000
b10111 -
1'
#2880000
0'
#2890000
b11000 -
1'
#2900000
0'
#2910000
b11001 -
1'
#2920000
0'
#2930000
b11010 -
1'
#2940000
0'
#2950000
b11011 -
1'
#2960000
0'
#2970000
b11100 -
1'
#2980000
0'
#2990000
b11101 -
1'
#3000000
0'
#3010000
b11110 -
1'
#3020000
0'
#3030000
b11111 -
1'
#3040000
0'
#3050000
b100000 -
1'
#3060000
0'
#3070000
b100001 -
1'
#3080000
0'
#3090000
b100010 -
1'
#3100000
0'
#3110000
b100011 -
1'
#3120000
0'
#3130000
b100100 -
1'
#3140000
0'
#3150000
b100101 -
1'
#3160000
0'
#3170000
b100110 -
1'
#3180000
0'
#3190000
b100111 -
1'
#3200000
0'
#3210000
b101000 -
1'
#3220000
0'
#3230000
b101001 -
1'
#3240000
0'
#3250000
b101010 -
1'
#3260000
0'
#3270000
b101011 -
1'
#3280000
0'
#3290000
b101100 -
1'
#3300000
0'
#3310000
b101101 -
1'
#3320000
0'
#3330000
b101110 -
1'
#3340000
0'
#3350000
b101111 -
1'
#3360000
0'
#3370000
b110000 -
1'
#3380000
0'
#3390000
b110001 -
1'
#3400000
0'
#3410000
b110010 -
1'
#3420000
0'
#3430000
b110011 -
1'
#3440000
0'
#3450000
b110100 -
1'
#3460000
0'
#3470000
b110101 -
1'
#3480000
0'
#3490000
b110110 -
1'
#3500000
0'
#3510000
b110111 -
1'
#3520000
0'
#3530000
b111000 -
1'
#3540000
0'
#3550000
b111001 -
1'
#3560000
0'
#3570000
b111010 -
1'
#3580000
0'
#3590000
b111011 -
1'
#3600000
0'
#3610000
b111100 -
1'
#3620000
0'
#3630000
b111101 -
1'
#3640000
0'
#3650000
b111110 -
1'
#3660000
0'
#3670000
b111111 -
1'
#3680000
0'
#3690000
b1000000 -
1'
#3700000
0'
#3710000
b1000001 -
1'
#3720000
0'
#3730000
b1000010 -
1'
#3740000
0'
#3750000
b1000011 -
1'
#3760000
0'
#3770000
b1000100 -
1'
#3780000
0'
#3790000
b1000101 -
1'
#3800000
0'
#3810000
b1000110 -
1'
#3820000
0'
#3830000
b1000111 -
1'
#3840000
0'
#3850000
b1001000 -
1'
#3860000
0'
#3870000
b1001001 -
1'
#3880000
0'
#3890000
b1001010 -
1'
#3900000
0'
#3910000
b1001011 -
1'
#3920000
0'
#3930000
b1001100 -
1'
#3940000
0'
#3950000
b1001101 -
1'
#3960000
0'
#3970000
b1001110 -
1'
#3980000
0'
#3990000
b1001111 -
1'
#4000000
0'
#4010000
b1010000 -
1'
#4020000
0'
#4030000
b1010001 -
1'
#4040000
0'
#4050000
b1010010 -
1'
#4060000
0'
#4070000
b1010011 -
1'
#4080000
0'
#4090000
b1010100 -
1'
#4100000
0'
#4110000
b1010101 -
1'
#4120000
0'
#4130000
b1010110 -
1'
#4140000
0'
#4150000
b1010111 -
1'
#4160000
0'
#4170000
b1011000 -
1'
#4180000
0'
#4190000
b1011001 -
1'
#4200000
0'
#4210000
b1011010 -
1'
#4220000
0'
#4230000
b1011011 -
1'
#4240000
0'
#4250000
b1011100 -
1'
#4260000
0'
#4270000
b1011101 -
1'
#4280000
0'
#4290000
b1011110 -
1'
#4300000
0'
#4310000
b1011111 -
1'
#4320000
0'
#4330000
b1100000 -
1'
#4340000
0'
#4350000
b1100001 -
1'
#4360000
0'
#4370000
b1100010 -
1'
#4380000
0'
#4390000
b1100011 -
1'
#4400000
0'
#4410000
1"
1#
0&
b0 -
b11 .
1'
#4420000
0'
#4430000
b1 -
1'
#4440000
0'
#4450000
b10 -
1'
#4460000
0'
#4470000
b11 -
1'
#4480000
0'
#4490000
b100 -
1'
#4500000
0'
#4510000
b101 -
1'
#4520000
0'
#4530000
b110 -
1'
#4540000
0'
#4550000
b111 -
1'
#4560000
0'
#4570000
b1000 -
1'
#4580000
0'
#4590000
b1001 -
1'
#4600000
0'
#4610000
b1010 -
1'
#4620000
0'
#4630000
b1011 -
1'
#4640000
0'
#4650000
b1100 -
1'
#4660000
0'
#4670000
b1101 -
1'
#4680000
0'
#4690000
b1110 -
1'
#4700000
0'
#4710000
b1111 -
1'
#4720000
0'
#4730000
b10000 -
1'
#4740000
0'
#4750000
b10001 -
1'
#4760000
0'
#4770000
b10010 -
1'
#4780000
0'
#4790000
b10011 -
1'
#4800000
0'
#4810000
1%
1$
0#
0"
b0 -
b0 .
1'
#4820000
0'
#4830000
b1 -
1'
#4840000
0'
#4850000
b10 -
1'
#4860000
0'
#4870000
b11 -
1'
#4880000
0'
#4890000
b100 -
1'
#4900000
0'
#4910000
b101 -
1'
#4920000
0'
#4930000
b110 -
1'
#4940000
0'
#4950000
b111 -
1'
#4960000
0'
#4970000
b1000 -
1'
#4980000
0'
#4990000
b1001 -
1'
